setup.py
sf_babel.egg-info/PKG-INFO
sf_babel.egg-info/SOURCES.txt
sf_babel.egg-info/dependency_links.txt
sf_babel.egg-info/namespace_packages.txt
sf_babel.egg-info/not-zip-safe
sf_babel.egg-info/requires.txt
sf_babel.egg-info/top_level.txt
sfext/__init__.py
sfext/babel/__init__.py
sfext/babel/babel.py
sfext/babel/wtformsupport.py